aioka-0.2.2.dist-info/METADATA
aioka-0.2.2.dist-info/WHEEL
aioka/__init__.py
aioka/action/base.py
aioka/action/master.py
aioka/handler/__init__.py
aioka/handler/base.py
aioka/middleware/__init__.py
aioka/middleware/base.py
aioka/server/__init__.py
aioka/server/app.py
aioka/server/base.py
aioka/server/errors/__init__.py
aioka/server/errors/fmt.py
aioka/server/errors/schema.py
aioka/server/master.py
aioka/server/schema.py
aioka-0.2.2.dist-info/RECORD
