Metadata-Version: 2.1
Name: aioka
Version: 0.2.2
Summary: aio-pika framework
Author-Email: Chebotarev Victor <powersemmi@gmail.com>
License: MIT
Requires-Python: >=3.11
Requires-Dist: aio-pika>=9.3.0
Requires-Dist: pytz>=2023.3.post1
Requires-Dist: pydantic>=2.4.2
Requires-Dist: uvicorn[standart]>=0.23.2
